<item>
<title>[COLOR white]The Incredibles (2004)[/COLOR]</title>
<link>https://uptobox.com/9wmb5idg5bhc</link>
<thumbnail>https://image.tmdb.org/t/p/original/9gBnaVySWaXulJNzR796Nd8kdje.jpg</thumbnail>
<fanart>https://image.tmdb.org/t/p/original/wnTFRPAQhNsxnPxWpIS8jFqE4Nd.jpg</fanart>
</item>

<item>
<title>[COLOR white]Incredibles 2 (2018)[/COLOR]</title>
<link>
<sublink>https://uptobox.com/hzqcvvn301b8</sublink>
</link>
<thumbnail>https://image.tmdb.org/t/p/original/9lFKBtaVIhP7E2Pk0IY1CwTKTMZ.jpg</thumbnail>
<fanart>https://image.tmdb.org/t/p/original/mabuNsGJgRuCTuGqjFkWe1xdu19.jpg</fanart>
</item>