<?xml version="1.0" encoding="UTF-8" standalone="yes" ?> 
<?xml-stylesheet href="hide-it.xsl" type="text/xsl"?>
<layoutype>fuckOFF</layoutype>
<item>
	<title>[COLOR orchid]¤[/COLOR] [B][COLOR white]49ers vs Buccaneers[/COLOR][/B] [COLOR orchid]¤[/COLOR]</title>
	<link>https://ok.ru/video/1814245673499</link>
	<thumbnail>https://bitbucket.org/threw/bluehat/raw/master/bg/nfl.png</thumbnail>
	<fanart>http://sportsmockery.com/wp-content/uploads/2016/06/nfl-field.jpg</fanart>
</item>
<item>
	<title>[COLOR orchid]¤[/COLOR] [B][COLOR white]Steelers vs Patriots[/COLOR][/B] [COLOR orchid]¤[/COLOR]</title>
	<link>https://ok.ru/video/1814245870107</link>
	<thumbnail>https://bitbucket.org/threw/bluehat/raw/master/bg/nfl.png</thumbnail>
	<fanart>http://sportsmockery.com/wp-content/uploads/2016/06/nfl-field.jpg</fanart>
</item>
<item>
	<title>[COLOR orchid]¤[/COLOR] [B][COLOR white]Giants vs Cowboys[/COLOR][/B] [COLOR orchid]¤[/COLOR]</title>
	<link>https://ok.ru/video/1814245476891</link>
	<thumbnail>https://bitbucket.org/threw/bluehat/raw/master/bg/nfl.png</thumbnail>
	<fanart>http://sportsmockery.com/wp-content/uploads/2016/06/nfl-field.jpg</fanart>
</item>
<item>
	<title>[COLOR orchid]¤[/COLOR] [B][COLOR white]Lions vs Cardinals[/COLOR][/B] [COLOR orchid]¤[/COLOR]</title>
	<link>https://ok.ru/video/1814246001179</link>
	<thumbnail>https://bitbucket.org/threw/bluehat/raw/master/bg/nfl.png</thumbnail>
	<fanart>http://sportsmockery.com/wp-content/uploads/2016/06/nfl-field.jpg</fanart>
</item>
<item>
	<title>[COLOR orchid]¤[/COLOR] [B][COLOR white]Redskins vs Eagles[/COLOR][/B] [COLOR orchid]¤[/COLOR]</title>
	<link>https://ok.ru/video/1814245804571</link>
	<thumbnail>https://bitbucket.org/threw/bluehat/raw/master/bg/nfl.png</thumbnail>
	<fanart>http://sportsmockery.com/wp-content/uploads/2016/06/nfl-field.jpg</fanart>
</item>
<item>
	<title>[COLOR orchid]¤[/COLOR] [B][COLOR white]Colts vs Chargers[/COLOR][/B] [COLOR orchid]¤[/COLOR]</title>
	<link>https://ok.ru/video/1814245280283</link>
	<thumbnail>https://bitbucket.org/threw/bluehat/raw/master/bg/nfl.png</thumbnail>
	<fanart>http://sportsmockery.com/wp-content/uploads/2016/06/nfl-field.jpg</fanart>
</item>
<item>
	<title>[COLOR orchid]¤[/COLOR] [B][COLOR white]Chiefs vs Jaguars[/COLOR][/B] [COLOR orchid]¤[/COLOR]</title>
	<link>https://ok.ru/video/1814245345819</link>
	<thumbnail>https://bitbucket.org/threw/bluehat/raw/master/bg/nfl.png</thumbnail>
	<fanart>http://sportsmockery.com/wp-content/uploads/2016/06/nfl-field.jpg</fanart>
</item>
<item>
	<title>[COLOR orchid]¤[/COLOR] [B][COLOR white]Bengals vs Seahawks[/COLOR][/B] [COLOR orchid]¤[/COLOR]</title>
	<link>https://ok.ru/video/1814245542427</link>
	<thumbnail>https://bitbucket.org/threw/bluehat/raw/master/bg/nfl.png</thumbnail>
	<fanart>http://sportsmockery.com/wp-content/uploads/2016/06/nfl-field.jpg</fanart>
</item>
<item>
	<title>[COLOR orchid]¤[/COLOR] [B][COLOR white]Bills vs Jets[/COLOR][/B] [COLOR orchid]¤[/COLOR]</title>
	<link>https://ok.ru/video/1814245411355</link>
	<thumbnail>https://bitbucket.org/threw/bluehat/raw/master/bg/nfl.png</thumbnail>
	<fanart>http://sportsmockery.com/wp-content/uploads/2016/06/nfl-field.jpg</fanart>
</item>
<item>
	<title>[COLOR orchid]¤[/COLOR] [B][COLOR white]Ravens vs Dolphins[/COLOR][/B] [COLOR orchid]¤[/COLOR]</title>
	<link>https://ok.ru/video/1814245607963</link>
	<thumbnail>https://bitbucket.org/threw/bluehat/raw/master/bg/nfl.png</thumbnail>
	<fanart>http://sportsmockery.com/wp-content/uploads/2016/06/nfl-field.jpg</fanart>
</item>
<item>
	<title>[COLOR orchid]¤[/COLOR] [B][COLOR white]Falcons vs Vikings[/COLOR][/B] [COLOR orchid]¤[/COLOR]</title>
	<link>https://ok.ru/video/1814245214747</link>
	<thumbnail>https://bitbucket.org/threw/bluehat/raw/master/bg/nfl.png</thumbnail>
	<fanart>http://sportsmockery.com/wp-content/uploads/2016/06/nfl-field.jpg</fanart>
</item>
<item>
	<title>[COLOR orchid]¤[/COLOR] [B][COLOR white]Rams vs Panthers[/COLOR][/B] [COLOR orchid]¤[/COLOR]</title>
	<link>https://ok.ru/video/1814245935643</link>
	<thumbnail>https://bitbucket.org/threw/bluehat/raw/master/bg/nfl.png</thumbnail>
	<fanart>http://sportsmockery.com/wp-content/uploads/2016/06/nfl-field.jpg</fanart>
</item>
<item>
	<title>[COLOR orchid]¤[/COLOR] [B][COLOR white]Titans vs Browns[/COLOR][/B] [COLOR orchid]¤[/COLOR]</title>
	<link>https://ok.ru/video/1814245935643</link>
	<thumbnail>https://bitbucket.org/threw/bluehat/raw/master/bg/nfl.png</thumbnail>
	<fanart>http://sportsmockery.com/wp-content/uploads/2016/06/nfl-field.jpg</fanart>
</item>
<item>
	<title>[COLOR orchid]¤[/COLOR] [B][COLOR white]Packers vs Bears[/COLOR][/B] [COLOR orchid]¤[/COLOR]</title>
	<link>https://ok.ru/video/1811857017371</link>
	<thumbnail>https://bitbucket.org/threw/bluehat/raw/master/bg/nfl.png</thumbnail>
	<fanart>http://sportsmockery.com/wp-content/uploads/2016/06/nfl-field.jpg</fanart>
</item>

