<item>
	<title>[COLOR=gainsboro]Once Upon a Time... in Hollywood[/COLOR]</title>
	<meta>
	<imdb>tt7131622</imdb>
	<content>movie</content>
	<title>Once Upon a Time... in Hollywood</title>
	<year>2019</year>
	</meta>
	<link>
	<sublink>search</sublink>
	<sublink>searchsd</sublink>
	</link>
	<thumbnail>https://image.tmdb.org/t/p/w1280/8j58iEBw9pOXFD2L0nt0ZXeHviB.jpg</thumbnail>
	<fanart>https://image.tmdb.org/t/p/original/rukEbPmQuMcP8oROEO5ayAy29mG.jpg</fanart>
</item>
<item>
	<title>[COLOR=gainsboro]The Hateful Eight[/COLOR]</title>
	<meta>
	<imdb>tt3460252</imdb>
	<content>movie</content>
	<title>The Hateful Eight</title>
	<year>2015</year>
	</meta>
	<link>
	<sublink>search</sublink>
	<sublink>searchsd</sublink>
	</link>
	<thumbnail>https://image.tmdb.org/t/p/w1280/nZeKw2oDiODgnht9OrohB2jBhjq.jpg</thumbnail>
	<fanart>https://image.tmdb.org/t/p/w1280/s6hTk2TlbvaSxNbcLHKsfQoAaoi.jpg</fanart>
</item>
<item>
	<title>[COLOR=gainsboro]Django Unchained[/COLOR]</title>
	<meta>
	<imdb>tt1853728</imdb>
	<content>movie</content>
	<title>Django Unchained</title>
	<year>2012</year>
	</meta>
	<link>
	<sublink>search</sublink>
	<sublink>searchsd</sublink>
	</link>
	<thumbnail>https://image.tmdb.org/t/p/w1280/7oWY8VDWW7thTzWh3OKYRkWUlD5.jpg</thumbnail>
	<fanart>https://image.tmdb.org/t/p/w1280/s4cJQaj40SwMifUrrdtdOJsjnRO.jpg</fanart>
</item>
<item>
	<title>[COLOR=gainsboro]Inglourious Basterds[/COLOR]</title>
	<meta>
	<imdb>tt0361748</imdb>
	<content>movie</content>
	<title>Inglourious Basterds</title>
	<year>2009</year>
	</meta>
	<link>
	<sublink>search</sublink>
	<sublink>searchsd</sublink>
	</link>
	<thumbnail>https://image.tmdb.org/t/p/w1280/7sfbEnaARXDDhKm0CZ7D7uc2sbo.jpg</thumbnail>
	<fanart>https://image.tmdb.org/t/p/w1280/8pEnePgGyfUqj8Qa6d91OZQ6Aih.jpg</fanart>
</item>
<item>
	<title>[COLOR=gainsboro]Death Proof[/COLOR]</title>
	<meta>
	<imdb>tt1028528</imdb>
	<content>movie</content>
	<title>Death Proof</title>
	<year>2007</year>
	</meta>
	<link>
	<sublink>search</sublink>
	<sublink>searchsd</sublink>
	</link>
	<thumbnail>https://image.tmdb.org/t/p/w1280/iy6016EG1Zt44tFyxc0rATKL2hr.jpg</thumbnail>
	<fanart>https://i.imgur.com/2Qo5Dgv.jpg</fanart>
</item>
<item>
	<title>[COLOR=gainsboro]Sin City[/COLOR]</title>
	<meta>
	<imdb>tt0401792</imdb>
	<content>movie</content>
	<title>Sin City</title>
	<year>2005</year>
	</meta>
	<link>
	<sublink>search</sublink>
	<sublink>searchsd</sublink>
	</link>
	<thumbnail>https://image.tmdb.org/t/p/w1280/8qGW691AOyqbKsEhpe7nHwMEbRe.jpg</thumbnail>
	<fanart>https://image.tmdb.org/t/p/w1280/h7EkLFDAQGrebhooz1G6qZenQFl.jpg</fanart>
</item>
<item>
	<title>[COLOR=gainsboro]Kill Bill: Vol. 1[/COLOR]</title>
	<meta>
	<imdb>tt0266697</imdb>
	<content>movie</content>
	<title>Kill Bill: Vol. 1</title>
	<year>2003</year>
	</meta>
	<link>
	<sublink>search</sublink>
	<sublink>searchsd</sublink>
	</link>
	<thumbnail>https://image.tmdb.org/t/p/w1280/v7TaX8kXMXs5yFFGR41guUDNcnB.jpg</thumbnail>
	<fanart>https://i.imgur.com/ltHeVhn.jpg</fanart>
</item>
<item>
	<title>[COLOR=gainsboro]Kill Bill: Vol. 2[/COLOR]</title>
	<meta>
	<imdb>tt0378194</imdb>
	<content>movie</content>
	<title>Kill Bill: Vol. 2</title>
	<year>2004</year>
	</meta>
	<link>
	<sublink>search</sublink>
	<sublink>searchsd</sublink>
	</link>
	<thumbnail>https://image.tmdb.org/t/p/w1280/2yhg0mZQMhDyvUQ4rG1IZ4oIA8L.jpg</thumbnail>
	<fanart>https://image.tmdb.org/t/p/w1280/70EtzaGfO2d8X5n8SLI4s61KuJh.jpg</fanart>
</item>
<item>
	<title>[COLOR=gainsboro]Jackie Brown[/COLOR]</title>
	<meta>
	<imdb>tt0119396</imdb>
	<content>movie</content>
	<title>Jackie Brown</title>
	<year>1997</year>
	</meta>
	<link>
	<sublink>search</sublink>
	<sublink>searchsd</sublink>
	</link>
	<thumbnail>https://image.tmdb.org/t/p/w1280/ewbLUXvm4riZL0aepy90o0vMesn.jpg</thumbnail>
	<fanart>https://i.imgur.com/KvA5Itf.jpg</fanart>
</item>
<item>
	<title>[COLOR=gainsboro]Reservoir Dogs[/COLOR]</title>
	<meta>
	<imdb>tt0105236</imdb>
	<content>movie</content>
	<title>Reservoir Dogs</title>
	<year>1992</year>
	</meta>
	<link>
	<sublink>search</sublink>
	<sublink>searchsd</sublink>
	</link>
	<thumbnail>https://image.tmdb.org/t/p/w1280/hzeOauJSD61dyTNy0NZIGUhj4uu.jpg</thumbnail>
	<fanart>https://image.tmdb.org/t/p/w1280/xPMbNZwn1nQzc5fsjnhuu3fDndA.jpg</fanart>
</item>
<item>
	<title>[COLOR=gainsboro]Pulp Fiction[/COLOR]</title>
	<meta>
	<imdb>tt0110912</imdb>
	<content>movie</content>
	<title>Pulp Fiction</title>
	<year>1994</year>
	</meta>
	<link>
	<sublink>search</sublink>
	<sublink>searchsd</sublink>
	</link>
	<thumbnail>https://image.tmdb.org/t/p/w1280/d5iIlFn5s0ImszYzBPb8JPIfbXD.jpg</thumbnail>
	<fanart>https://image.tmdb.org/t/p/w1280/suaEOtk1N1sgg2MTM7oZd2cfVp3.jpg</fanart>
</item>
<item>
	<title>[COLOR=gainsboro]Planet Terror[/COLOR]</title>
	<meta>
	<imdb>tt1077258</imdb>
	<content>movie</content>
	<title>Planet Terror</title>
	<year>2007</year>
	</meta>
	<link>
	<sublink>search</sublink>
	<sublink>searchsd</sublink>
	</link>
	<thumbnail>https://image.tmdb.org/t/p/w1280/30ANoUgvqQZ9tgCnM6OyJZUveaf.jpg</thumbnail>
	<fanart>https://image.tmdb.org/t/p/w1280/bUmaGlXAtAizyo6zArOP2YDVKZB.jpg</fanart>
</item>
<item>
	<title>[COLOR=gainsboro]Grindhouse[/COLOR]</title>
	<meta>
	<imdb>tt0462322</imdb>
	<content>movie</content>
	<title>Grindhouse</title>
	<year>2007</year>
	</meta>
	<link>
	<sublink>search</sublink>
	<sublink>searchsd</sublink>
	</link>
	<thumbnail>https://image.tmdb.org/t/p/w1280/jl3K6T8Mridd2dWmcdBpKyHyt6Y.jpg</thumbnail>
	<fanart>https://image.tmdb.org/t/p/w1280/zhNJ1SQwIh2EpTst9ofaAHRV2UL.jpg</fanart>
</item>
<item>
	<title>[COLOR=gainsboro]Hostel[/COLOR]</title>
	<meta>
	<imdb>tt0450278</imdb>
	<content>movie</content>
	<title>Hostel</title>
	<year>2006</year>
	</meta>
	<link>
	<sublink>search</sublink>
	<sublink>searchsd</sublink>
	</link>
	<thumbnail>https://image.tmdb.org/t/p/w1280/dDrtuWUKhgUGp12kgUWuP0NpTdF.jpg</thumbnail>
	<fanart>https://image.tmdb.org/t/p/w1280/AuXfRrQI35oQ5z2UpHnrWBmS8uK.jpg</fanart>
</item>
<item>
	<title>[COLOR=gainsboro]Hostel: Part II[/COLOR]</title>
	<meta>
	<imdb>tt0498353</imdb>
	<content>movie</content>
	<title>Hostel: Part II</title>
	<year>2007</year>
	</meta>
	<link>
	<sublink>search</sublink>
	<sublink>searchsd</sublink>
	</link>
	<thumbnail>https://image.tmdb.org/t/p/w1280/4vypgqZRaVpeMDyjqCJSUNKSAeU.jpg</thumbnail>
	<fanart>https://image.tmdb.org/t/p/w1280/7MorkyWQXVOi2XKYci6pIGbjb2x.jpg</fanart>
</item>
<item>
	<title>[COLOR=gainsboro]From Dusk Till Dawn[/COLOR]</title>
	<meta>
	<imdb>tt0116367</imdb>
	<content>movie</content>
	<title>From Dusk Till Dawn</title>
	<year>1996</year>
	</meta>
	<link>
	<sublink>search</sublink>
	<sublink>searchsd</sublink>
	</link>
	<thumbnail>https://image.tmdb.org/t/p/w1280/sV3kIAmvJ9tPz4Lq5fuf9LLMxte.jpg</thumbnail>
	<fanart>https://image.tmdb.org/t/p/w1280/lYVVFWqLXaZAdACwf8YNStEmPHn.jpg</fanart>
</item>
<item>
	<title>[COLOR=gainsboro]Natural Born Killers[/COLOR]</title>
	<meta>
	<imdb>tt0110632</imdb>
	<content>movie</content>
	<title>Natural Born Killers</title>
	<year>1994</year>
	</meta>
	<link>
	<sublink>search</sublink>
	<sublink>searchsd</sublink>
	</link>
	<thumbnail>https://image.tmdb.org/t/p/w1280/a0UUOtgSWRmRIHRbkImxkgZYrF.jpg</thumbnail>
	<fanart>https://i.imgur.com/VZZmKev.jpg</fanart>
</item>
<item>
	<title>[COLOR=gainsboro]True Romance[/COLOR]</title>
	<meta>
	<imdb>tt0108399</imdb>
	<content>movie</content>
	<title>True Romance</title>
	<year>1993</year>
	</meta>
	<link>
	<sublink>search</sublink>
	<sublink>searchsd</sublink>
	</link>
	<thumbnail>https://image.tmdb.org/t/p/w1280/AqlPzcILRi0IW0JodKp7pMMNEFt.jpg</thumbnail>
	<fanart>https://image.tmdb.org/t/p/w1280/5f0B7cRa0oWAWPgCsLmIZ7gAGpC.jpg</fanart>
</item>
<item>
	<title>[COLOR=gainsboro]My Best Friend's Birthday[/COLOR]</title>
	<meta>
	<imdb>tt0359715</imdb>
	<content>movie</content>
	<title>My Best Friend's Birthday</title>
	<year>1987</year>
	</meta>
	<link>
	<sublink>search</sublink>
	<sublink>searchsd</sublink>
	</link>
	<thumbnail>https://image.tmdb.org/t/p/w1280/8OQ8GCf5x1cFtzzo3gz6rZJr7nx.jpg</thumbnail>
	<fanart>https://i.imgur.com/Vn1Gf2W.jpg</fanart>
</item>
<item>
	<title>[COLOR=gainsboro]Four Rooms[/COLOR]</title>
	<meta>
	<imdb>tt0113101</imdb>
	<content>movie</content>
	<title>Four Rooms</title>
	<year>1995</year>
	</meta>
	<link>
	<sublink>search</sublink>
	<sublink>searchsd</sublink>
	</link>
	<thumbnail>https://image.tmdb.org/t/p/w1280/xhU6hPDnk4s8iWWKoq4oEmNI600.jpg</thumbnail>
	<fanart>https://image.tmdb.org/t/p/w1280/xvjGhJHsArVjCWXb5OARi0PiqvB.jpg</fanart>
</item>
<item>
	<title>[COLOR=gainsboro]Killing Zoe[/COLOR]</title>
	<meta>
	<imdb>tt0110265</imdb>
	<content>movie</content>
	<title>Killing Zoe</title>
	<year>1993</year>
	</meta>
	<link>
	<sublink>search</sublink>
	<sublink>searchsd</sublink>
	</link>
	<thumbnail>https://image.tmdb.org/t/p/w1280/k3UEKMVnkljOlsO5sLmz87YGlaG.jpg</thumbnail>
	<fanart>https://i.imgur.com/coJGjAE.jpg</fanart>
</item>
<item>
	<title>[COLOR=gainsboro]Past Midnight[/COLOR]</title>
	<meta>
	<imdb>tt0105108</imdb>
	<content>movie</content>
	<title>Past Midnight</title>
	<year>1991</year>
	</meta>
	<link>
	<sublink>search</sublink>
	<sublink>searchsd</sublink>
	</link>
	<thumbnail>https://image.tmdb.org/t/p/w1280/8sMb6VIWs253IZ0X56vC6v7FjnB.jpg</thumbnail>
	<fanart>https://i.imgur.com/8rJ2B7W.jpg</fanart>
</item>
<item>
	<title>[COLOR=gainsboro]Quentin Tarantino: 20 Years of Filmmaking[/COLOR]</title>
	<meta>
	<imdb>tt6021960</imdb>
	<content>movie</content>
	<title>Quentin Tarantino: 20 Years of Filmmaking</title>
	<year>2012</year>
	</meta>
	<link>
	<sublink>search</sublink>
	<sublink>searchsd</sublink>
	</link>
	<thumbnail>https://image.tmdb.org/t/p/w1280/puLHiMjLnz3nrrslemC1P3p38MB.jpg</thumbnail>
	<fanart>https://i.imgur.com/oRpjqhB.jpg</fanart>
</item>
<item>
	<title>[COLOR=gainsboro]QT8: The First Eight[/COLOR]</title>
	<meta>
	<imdb>tt4329810</imdb>
	<content>movie</content>
	<title>QT8: The First Eight</title>
	<year>2019</year>
	</meta>
	<link>
	<sublink>search</sublink>
	<sublink>searchsd</sublink>
	</link>
	<thumbnail>https://image.tmdb.org/t/p/w1280/rGPwMYUeygsUAmo0NS8IPlhQEfH.jpg</thumbnail>
	<fanart>https://image.tmdb.org/t/p/w1280/ulKw0ytuwp9L2RmikvO3mg8Ll6b.jpg</fanart>
</item>

<item>
	<title>[COLOR=gainsboro]Celluloid Horror[/COLOR]</title>
	<meta>
	<imdb>tt0441848</imdb>
	<content>movie</content>
	<title>Celluloid Horror</title>
	<year>2004</year>
	</meta>
	<link>
	<sublink>search</sublink>
	<sublink>searchsd</sublink>
	</link>
	<thumbnail>https://i.imgur.com/iEQ2uWK.jpg</thumbnail>
	<fanart>https://i.imgur.com/77dnj1W.jpg</fanart>
</item>
<item>
	<title>[COLOR=gainsboro]CSI Las Vegas: Grave Danger[/COLOR]</title>
	<meta>
	<imdb>tt0534695</imdb>
	<content>movie</content>
	<title>CSI Las Vegas: Grave Danger</title>
	<year>2005</year>
	</meta>
	<link>
	<sublink>search</sublink>
	<sublink>searchsd</sublink>
	</link>
	<thumbnail>https://i.imgur.com/sVAJaAP.jpg</thumbnail>
	<fanart>https://i.imgur.com/d0VriM6.jpg</fanart>
</item>															  
<item>	  
	<title>[COLOR=gainsboro]CSI: Grave Danger: Part 2[/COLOR]</title>
	<meta>
	<imdb>tt0534696</imdb>
	<content>movie</content>
	<title>CSI: Grave Danger: Part 2</title>
	<year>2005</year>
	</meta>
	<link>
	<sublink>search</sublink>
	<sublink>searchsd</sublink>
	</link>
	<thumbnail>https://i.imgur.com/sVAJaAP.jpg</thumbnail>
	<fanart>https://i.imgur.com/d0VriM6.jpg</fanart>
</item>
