<item>
	<title>Private Gold 02:Friends In Sex</title>
	<link>
	<sublinkTrailer>https://trailer.adultempire.com/hls/preview/644050/master.m3u8</sublink>
	<sublink>https://uptobox.com/cll64t0w5383</sublink>
	<sublink>https://streamango.com/f/abpltnpaaqaadfkt/Private_-_Gold_02_-_Friends_in_Sex_avi</sublink>
	</link>
	<thumbnail>https://imgs1cdn.adultempire.com/products/96/26796h.jpg</thumbnail>
	<fanart></fanart>
</item>

<item>
	<title>Private Gold 03:Chase</title>
	<link>
	<sublink>https://uptobox.com/kkvjz561b9al</sublink>
	<sublink>https://uptostream.com/kkvjz561b9al</sublink>
	<sublink>https://streamango.com/f/rqelltqsrmoerdkn/Private_-_Gold_03_-_Chase_avi</sublink>
	</link>
	<thumbnail>https://image.tmdb.org/t/p/w600_and_h900_bestv2/2jmAzFvckJ0IAuDFLaAI0NPYQ8v.jpg</thumbnail>
	<fanart></fanart>
</item>

<item>
	<title>Private Gold 07:Kruger Park</title>
	<link>
	<sublink>https://uptobox.com/eq4me735b4h7</sublink>
	<sublink>https://streamango.com/f/qpbamacdmtclseds/Private_-_Gold_07_-_Kruger_Park_avi</sublink>
	</link>
	<thumbnail>https://image.tmdb.org/t/p/w600_and_h900_bestv2/lZZvA2EMum4X5IL07eRgeVkF4rR.jpg</thumbnail>
	<fanart></fanart>
</item>

<item>
	<title>Private Gold 10:Sins</title>
	<link>
	<sublink>https://uptobox.com/5y3x2265ks5b</sublink>
	<sublink>https://streamango.com/f/elloblkcsdrsqmrs/Private_-_Gold_10_-_Sins_avi</sublink>
	</link>
	<thumbnail>https://image.tmdb.org/t/p/w600_and_h900_bestv2/4YdRDee1XJwSIjUMPchSdfbnNze.jpg</thumbnail>
	<fanart></fanart>
</item>

<item>
	<title>Private Gold 11:Pyramid</title>
	<link>
	<sublink>https://uptobox.com/fvbv20g9uhpn</sublink>
	<sublink>https://streamango.com/f/lpdnfoqfqffddlpc/Private_-_Gold_11_-_Pyramid_avi</sublink>
	</link>
	<thumbnail>https://image.tmdb.org/t/p/w600_and_h900_bestv2/4fuK5jZWQGWpOfp3dvckgNdzdeE.jpg</thumbnail>
	<fanart></fanart>
</item>

<item>
	<title>Private Gold 12: Pyramid 2</title>
	<link>
	<sublink>https://uptobox.com/ys60eefd65vs</sublink>
	<sublink>https://streamango.com/f/snptopkbrkokbmoq/Private_-_Gold_12_-_Pyramid_2_avi</sublink>
	</link>
	<thumbnail>https://i110.fastpic.ru/big/2019/0524/c1/a0ef763de3c4c9114ec8ae9df10b3bc1.jpg</thumbnail>
	<fanart></fanart>
</item>
<item>
	<title>Private Gold 14: Sweet Baby</title>
	<link>
	<sublink>https://uptobox.com/hmf8myfpy9lp</sublink>
	<sublink>https://streamango.com/f/erfnobbaldrtkeqf/Private_-_Gold_14_-_Sweet_Lady_avi</sublink>
	</link>
	<thumbnail>https://image.tmdb.org/t/p/w600_and_h900_bestv2/enRf4WLtHlbhe2OByUmbnS7julp.jpg</thumbnail>
	<fanart></fanart>
</item>